{
  "environment": "web",
  "format": "html",
  "prefix": "https://storage.googleapis.com",
  "mainga": "UA-49880327-14",
  "updated": "2020-05-10T14:46:39+01:00",
  "id": "part-7",
  "duration": 190,
  "title": "Part 7",
  "summary": "In the seventh part of the course we’ll focus on general programming paradigms and algorithms.",
  "source": "part-7.md",
  "theme": "",
  "status": [
    "published"
  ],
  "category": [
    "python-programming"
  ],
  "tags": [
    "web"
  ],
  "feedback": "https://github.com/Scott3142/python-programming",
  "ga": "UA-49751789-4",
  "url": "part-7"
}
